examples/skytem_example.py
gatdaem1d/__init__.py
gatdaem1d/gatdaem1d.dll
gatdaem1d/libfftw3-3.dll
gatdaem1d/libfftw3f-3.dll
ga_aem_forward_win-3.0.2a0.dist-info/METADATA
ga_aem_forward_win-3.0.2a0.dist-info/WHEEL
ga_aem_forward_win-3.0.2a0.dist-info/top_level.txt
ga_aem_forward_win-3.0.2a0.dist-info/RECORD
