Metadata-Version: 2.2
Name: ga-aem-forward-win
Version: 3.0.2a0
Summary: Time-domain airborne electromagnetic forward modelling for Windows. Corresponds to v2.0.3 of the GA-AEM code
Author-email: Ross C Brodie <ross.c.brodie@ga.gov.au>
Keywords: electromagnetic,geophysics
Classifier: License :: OSI Approved
Classifier: License :: OSI Approved :: GNU General Public License v2 (GPLv2)
Classifier: Programming Language :: Python :: 3
Classifier: Topic :: Scientific/Engineering :: Physics
Classifier: Operating System :: Microsoft :: Windows
Classifier: Operating System :: Microsoft :: Windows :: Windows 10
Classifier: Operating System :: Microsoft :: Windows :: Windows 11
Requires-Python: >=3.10
Requires-Dist: numpy
Requires-Dist: matplotlib
